qr2022/Data_Encoding.py
qr2022/Data_analysis.py
qr2022/Error_Correction_Coding.py
qr2022/Module_Placement.py
qr2022/Structure_Final_Message.py
qr2022/__init__.py
qr2022/constants.py
qr2022-0.0.1.dist-info/METADATA
qr2022-0.0.1.dist-info/WHEEL
qr2022-0.0.1.dist-info/top_level.txt
qr2022-0.0.1.dist-info/zip-safe
qr2022-0.0.1.dist-info/RECORD
