Metadata-Version: 2.1
Name: qr2022
Version: 0.0.1
Summary: Generate QR code of the given string.
Home-page: https://github.com/HellOwhatAs/qr2022
Author: xjq
Author-email: xjq701229@outlook.com
License: UNKNOWN
Platform: UNKNOWN
Classifier: Programming Language :: Python :: 3
Requires-Dist: opencv-python
